{
    "asset": {
        "format": "png",
        "id": "05c6dc988d7404a4d6fd46adc969f65d",
        "name": "2020-12-08T00-03-55.510.png",
        "path": "file:D:/C%23/WebScraper/WebScraper.ML.DatasetGenerator/Data/Images/2020-12-08T00-03-55.510.png",
        "size": {
            "width": 1920,
            "height": 937
        },
        "state": 2,
        "type": 1
    },
    "regions": [
        {
            "id": "ZsXTtFywk",
            "type": "RECTANGLE",
            "tags": [
                "price"
            ],
            "boundingBox": {
                "height": 37.10891089108911,
                "width": 169.72375690607734,
                "left": 1230.4972375690606,
                "top": 432.48861828147096
            },
            "points": [
                {
                    "x": 1230.4972375690606,
                    "y": 432.48861828147096
                },
                {
                    "x": 1400.220994475138,
                    "y": 432.48861828147096
                },
                {
                    "x": 1400.220994475138,
                    "y": 469.5975291725601
                },
                {
                    "x": 1230.4972375690606,
                    "y": 469.5975291725601
                }
            ]
        },
        {
            "id": "OP_JnqMn0",
            "type": "RECTANGLE",
            "tags": [
                "name"
            ],
            "boundingBox": {
                "height": 33.15538461538461,
                "width": 704.8648648648648,
                "left": 209.009009009009,
                "top": 285.46966346153846
            },
            "points": [
                {
                    "x": 209.009009009009,
                    "y": 285.46966346153846
                },
                {
                    "x": 913.8738738738738,
                    "y": 285.46966346153846
                },
                {
                    "x": 913.8738738738738,
                    "y": 318.62504807692306
                },
                {
                    "x": 209.009009009009,
                    "y": 318.62504807692306
                }
            ]
        }
    ],
    "version": "2.2.0"
}