{
    "asset": {
        "format": "png",
        "id": "21b3beca87cb7f9c4c4dbf430a6203b2",
        "name": "2020-12-08T00-03-55.2734.png",
        "path": "file:D:/C%23/WebScraper/WebScraper.ML.DatasetGenerator/Data/Images/2020-12-08T00-03-55.2734.png",
        "size": {
            "width": 1917,
            "height": 933
        },
        "state": 2,
        "type": 1
    },
    "regions": [
        {
            "id": "Pcvscxo21",
            "type": "RECTANGLE",
            "tags": [
                "price"
            ],
            "boundingBox": {
                "height": 28.080632571876333,
                "width": 67.51864640883979,
                "left": 1217.9834254143645,
                "top": 351.19840425531913
            },
            "points": [
                {
                    "x": 1217.9834254143645,
                    "y": 351.19840425531913
                },
                {
                    "x": 1285.5020718232045,
                    "y": 351.19840425531913
                },
                {
                    "x": 1285.5020718232045,
                    "y": 379.2790368271955
                },
                {
                    "x": 1217.9834254143645,
                    "y": 379.2790368271955
                }
            ]
        },
        {
            "id": "f-UhKd71B",
            "type": "RECTANGLE",
            "tags": [
                "name"
            ],
            "boundingBox": {
                "height": 31.71671388101983,
                "width": 630.1922811853894,
                "left": 215.3487250172295,
                "top": 211.5893015226629
            },
            "points": [
                {
                    "x": 215.3487250172295,
                    "y": 211.5893015226629
                },
                {
                    "x": 845.541006202619,
                    "y": 211.5893015226629
                },
                {
                    "x": 845.541006202619,
                    "y": 243.30601540368272
                },
                {
                    "x": 215.3487250172295,
                    "y": 243.30601540368272
                }
            ]
        }
    ],
    "version": "2.2.0"
}