{
    "asset": {
        "format": "png",
        "id": "21d9b8a164036013b15cf89802117681",
        "name": "2020-12-08T00-03-55.448.png",
        "path": "file:D:/C%23/WebScraper/WebScraper.ML.DatasetGenerator/Data/Images/2020-12-08T00-03-55.448.png",
        "size": {
            "width": 1920,
            "height": 939
        },
        "state": 2,
        "type": 1
    },
    "regions": [
        {
            "id": "EsoJ2MDpX",
            "type": "RECTANGLE",
            "tags": [
                "price"
            ],
            "boundingBox": {
                "height": 39.78813559322034,
                "width": 112.70718232044199,
                "left": 1363.0939226519336,
                "top": 374.1328125
            },
            "points": [
                {
                    "x": 1363.0939226519336,
                    "y": 374.1328125
                },
                {
                    "x": 1475.8011049723757,
                    "y": 374.1328125
                },
                {
                    "x": 1475.8011049723757,
                    "y": 413.9209480932203
                },
                {
                    "x": 1363.0939226519336,
                    "y": 413.9209480932203
                }
            ]
        },
        {
            "id": "dkxf4g4ez",
            "type": "RECTANGLE",
            "tags": [
                "price"
            ],
            "boundingBox": {
                "height": 19.838028169014084,
                "width": 55.57546519641627,
                "left": 1369.5382494831151,
                "top": 462.6600132042254
            },
            "points": [
                {
                    "x": 1369.5382494831151,
                    "y": 462.6600132042254
                },
                {
                    "x": 1425.1137146795315,
                    "y": 462.6600132042254
                },
                {
                    "x": 1425.1137146795315,
                    "y": 482.49804137323946
                },
                {
                    "x": 1369.5382494831151,
                    "y": 482.49804137323946
                }
            ]
        },
        {
            "id": "CPSvVAdAt",
            "type": "RECTANGLE",
            "tags": [
                "price"
            ],
            "boundingBox": {
                "height": 29.095774647887325,
                "width": 83.3631977946244,
                "left": 1368.2150241212958,
                "top": 731.1346610915493
            },
            "points": [
                {
                    "x": 1368.2150241212958,
                    "y": 731.1346610915493
                },
                {
                    "x": 1451.57822191592,
                    "y": 731.1346610915493
                },
                {
                    "x": 1451.57822191592,
                    "y": 760.2304357394366
                },
                {
                    "x": 1368.2150241212958,
                    "y": 760.2304357394366
                }
            ]
        },
        {
            "id": "mWzwAc8uk",
            "type": "RECTANGLE",
            "tags": [
                "name"
            ],
            "boundingBox": {
                "height": 28.847926267281107,
                "width": 580.9009009009009,
                "left": 239.27927927927928,
                "top": 234.70492511520737
            },
            "points": [
                {
                    "x": 239.27927927927928,
                    "y": 234.70492511520737
                },
                {
                    "x": 820.1801801801802,
                    "y": 234.70492511520737
                },
                {
                    "x": 820.1801801801802,
                    "y": 263.5528513824885
                },
                {
                    "x": 239.27927927927928,
                    "y": 263.5528513824885
                }
            ]
        }
    ],
    "version": "2.2.0"
}