{
    "asset": {
        "format": "png",
        "id": "23e59b0f60040685608f7142fd2761df",
        "name": "2020-12-08T00-03-55.59340.png",
        "path": "file:D:/C%23/WebScraper/WebScraper.ML.DatasetGenerator/Data/Images/2020-12-08T00-03-55.59340.png",
        "size": {
            "width": 1920,
            "height": 937
        },
        "state": 2,
        "type": 1
    },
    "regions": [
        {
            "id": "pkFJ7y8oH",
            "type": "RECTANGLE",
            "tags": [
                "price"
            ],
            "boundingBox": {
                "height": 31.762711864406782,
                "width": 84.68642315644384,
                "left": 1343.0737422467264,
                "top": 815.3256532485876
            },
            "points": [
                {
                    "x": 1343.0737422467264,
                    "y": 815.3256532485876
                },
                {
                    "x": 1427.7601654031703,
                    "y": 815.3256532485876
                },
                {
                    "x": 1427.7601654031703,
                    "y": 847.0883651129944
                },
                {
                    "x": 1343.0737422467264,
                    "y": 847.0883651129944
                }
            ]
        },
        {
            "id": "ZVrARBXg_",
            "type": "RECTANGLE",
            "tags": [
                "name"
            ],
            "boundingBox": {
                "height": 38.37994350282486,
                "width": 939.4900068917988,
                "left": 242.1502412129566,
                "top": 672.3934498587571
            },
            "points": [
                {
                    "x": 242.1502412129566,
                    "y": 672.3934498587571
                },
                {
                    "x": 1181.6402481047553,
                    "y": 672.3934498587571
                },
                {
                    "x": 1181.6402481047553,
                    "y": 710.773393361582
                },
                {
                    "x": 242.1502412129566,
                    "y": 710.773393361582
                }
            ]
        }
    ],
    "version": "2.2.0"
}