{
    "asset": {
        "format": "png",
        "id": "31e9497b44147b19ab8dcec2ba6ef022",
        "name": "2020-12-08T00-03-55.27845.png",
        "path": "file:D:/C%23/WebScraper/WebScraper.ML.DatasetGenerator/Data/Images/2020-12-08T00-03-55.27845.png",
        "size": {
            "width": 1919,
            "height": 941
        },
        "state": 2,
        "type": 1
    },
    "regions": [
        {
            "id": "2DF4rg8za",
            "type": "RECTANGLE",
            "tags": [
                "price"
            ],
            "boundingBox": {
                "height": 35.68398876404494,
                "width": 76.70709855272227,
                "left": 1225.9910406616127,
                "top": 319.5245128160112
            },
            "points": [
                {
                    "x": 1225.9910406616127,
                    "y": 319.5245128160112
                },
                {
                    "x": 1302.698139214335,
                    "y": 319.5245128160112
                },
                {
                    "x": 1302.698139214335,
                    "y": 355.2085015800562
                },
                {
                    "x": 1225.9910406616127,
                    "y": 355.2085015800562
                }
            ]
        },
        {
            "id": "uC-UefSGD",
            "type": "RECTANGLE",
            "tags": [
                "name"
            ],
            "boundingBox": {
                "height": 37.00561797752809,
                "width": 497.2736044107512,
                "left": 218.2184700206754,
                "top": 209.8292880969101
            },
            "points": [
                {
                    "x": 218.2184700206754,
                    "y": 209.8292880969101
                },
                {
                    "x": 715.4920744314267,
                    "y": 209.8292880969101
                },
                {
                    "x": 715.4920744314267,
                    "y": 246.83490607443818
                },
                {
                    "x": 218.2184700206754,
                    "y": 246.83490607443818
                }
            ]
        }
    ],
    "version": "2.2.0"
}